{
  "annotations": {
    "list": [
      {
        "builtIn": 1,
        "datasource": {
          "type": "datasource",
          "uid": "grafana"
        },
        "enable": true,
        "hide": true,
        "iconColor": "rgba(0, 211, 255, 1)",
        "name": "Annotations & Alerts",
        "type": "dashboard"
      }
    ]
  },
  "editable": true,
  "fiscalYearStartMonth": 0,
  "graphTooltip": 0,
  "id": null,
  "links": [],
  "liveNow": false,
  "panels": [
    {
      "datasource": {
        "type": "elasticsearch",
        "uid": "000000006"
      },
      "fieldConfig": {
        "defaults": {
          "color": {
            "mode": "palette-classic"
          },
          "custom": {
            "axisCenteredZero": false,
            "axisColorMode": "text",
            "axisLabel": "",
            "axisPlacement": "auto",
            "barAlignment": 0,
            "drawStyle": "line",
            "fillOpacity": 10,
            "gradientMode": "none",
            "hideFrom": {
              "legend": false,
              "tooltip": false,
              "viz": false
            },
            "lineInterpolation": "linear",
            "lineWidth": 1,
            "pointSize": 5,
            "scaleDistribution": {
              "type": "linear"
            },
            "showPoints": "never",
            "spanNulls": false,
            "stacking": {
              "group": "A",
              "mode": "none"
            },
            "thresholdsStyle": {
              "mode": "off"
            }
          },
          "mappings": [],
          "thresholds": {
            "mode": "absolute",
            "steps": [
              {
                "color": "green",
                "value": null
              },
              {
                "color": "red",
                "value": 80
              }
            ]
          },
          "unit": "short"
        },
        "overrides": []
      },
      "gridPos": {
        "h": 9,
        "w": 24,
        "x": 0,
        "y": 0
      },
      "id": 2,
      "links": [],
      "options": {
        "legend": {
          "calcs": [
            "mean",
            "lastNotNull",
            "max",
            "min",
            "sum"
          ],
          "displayMode": "table",
          "placement": "bottom",
          "showLegend": true
        },
        "tooltip": {
          "mode": "multi",
          "sort": "none"
        }
      },
      "pluginVersion": "9.5.7",
      "targets": [
        {
          "bucketAggs": [
            {
              "field": "@timestamp",
              "id": "2",
              "settings": {
                "interval": "1m",
                "min_doc_count": 0,
                "trimEdges": 0
              },
              "type": "date_histogram"
            }
          ],
          "datasource": {
            "type": "elasticsearch",
            "uid": "000000006"
          },
          "metrics": [
            {
              "field": "select field",
              "id": "1",
              "type": "count"
            }
          ],
          "query": "host.name:$apihost AND source.address:$clientip",
          "refId": "A",
          "timeField": "@timestamp"
        }
      ],
      "title": "API Querys per Minute",
      "type": "timeseries"
    },
    {
      "datasource": {
        "type": "elasticsearch",
        "uid": "000000006"
      },
      "fieldConfig": {
        "defaults": {
          "color": {
            "mode": "thresholds"
          },
          "custom": {
            "cellOptions": {
              "type": "auto"
            },
            "inspect": false
          },
          "decimals": 2,
          "displayName": "",
          "mappings": [],
          "thresholds": {
            "mode": "absolute",
            "steps": [
              {
                "color": "green",
                "value": null
              },
              {
                "color": "red",
                "value": 80
              }
            ]
          },
          "unit": "short"
        },
        "overrides": [
          {
            "matcher": {
              "id": "byName",
              "options": "Time"
            },
            "properties": [
              {
                "id": "displayName",
                "value": "Time"
              },
              {
                "id": "unit",
                "value": "time: YYYY-MM-DD HH:mm:ss"
              },
              {
                "id": "custom.align"
              }
            ]
          },
          {
            "matcher": {
              "id": "byName",
              "options": "Count"
            },
            "properties": [
              {
                "id": "unit",
                "value": "locale"
              },
              {
                "id": "decimals",
                "value": 2
              },
              {
                "id": "custom.align"
              }
            ]
          },
          {
            "matcher": {
              "id": "byName",
              "options": "http.response.status_code"
            },
            "properties": [
              {
                "id": "decimals"
              }
            ]
          }
        ]
      },
      "gridPos": {
        "h": 6,
        "w": 12,
        "x": 0,
        "y": 9
      },
      "id": 8,
      "links": [],
      "options": {
        "cellHeight": "sm",
        "footer": {
          "countRows": false,
          "fields": "",
          "reducer": [
            "sum"
          ],
          "show": false
        },
        "showHeader": true
      },
      "pluginVersion": "9.5.7",
      "targets": [
        {
          "bucketAggs": [
            {
              "field": "http.response.status_code",
              "id": "2",
              "settings": {
                "min_doc_count": 1,
                "order": "desc",
                "orderBy": "1",
                "size": "10"
              },
              "type": "terms"
            }
          ],
          "datasource": {
            "type": "elasticsearch",
            "uid": "000000006"
          },
          "metrics": [
            {
              "field": "select field",
              "id": "1",
              "type": "count"
            }
          ],
          "query": "host.name:$apihost AND source.address:$clientip",
          "refId": "A",
          "timeField": "@timestamp"
        }
      ],
      "title": "Hits by Response Code",
      "transformations": [
        {
          "id": "merge",
          "options": {
            "reducers": []
          }
        }
      ],
      "type": "table"
    },
    {
      "datasource": {
        "type": "elasticsearch",
        "uid": "000000006"
      },
      "fieldConfig": {
        "defaults": {
          "color": {
            "mode": "thresholds"
          },
          "custom": {
            "cellOptions": {
              "type": "auto"
            },
            "inspect": false
          },
          "decimals": 2,
          "displayName": "",
          "mappings": [],
          "thresholds": {
            "mode": "absolute",
            "steps": [
              {
                "color": "green",
                "value": null
              },
              {
                "color": "red",
                "value": 80
              }
            ]
          },
          "unit": "short"
        },
        "overrides": [
          {
            "matcher": {
              "id": "byName",
              "options": "Time"
            },
            "properties": [
              {
                "id": "displayName",
                "value": "Time"
              },
              {
                "id": "unit",
                "value": "time: YYYY-MM-DD HH:mm:ss"
              },
              {
                "id": "custom.align"
              }
            ]
          },
          {
            "matcher": {
              "id": "byName",
              "options": "Count"
            },
            "properties": [
              {
                "id": "unit",
                "value": "locale"
              },
              {
                "id": "decimals",
                "value": 2
              },
              {
                "id": "custom.align"
              }
            ]
          },
          {
            "matcher": {
              "id": "byName",
              "options": "host.name"
            },
            "properties": [
              {
                "id": "displayName",
                "value": "API Host"
              },
              {
                "id": "unit",
                "value": "short"
              },
              {
                "id": "decimals",
                "value": 2
              },
              {
                "id": "custom.align"
              }
            ]
          }
        ]
      },
      "gridPos": {
        "h": 6,
        "w": 12,
        "x": 12,
        "y": 9
      },
      "id": 5,
      "links": [],
      "options": {
        "cellHeight": "sm",
        "footer": {
          "countRows": false,
          "fields": "",
          "reducer": [
            "sum"
          ],
          "show": false
        },
        "showHeader": true
      },
      "pluginVersion": "9.5.7",
      "targets": [
        {
          "bucketAggs": [
            {
              "field": "host.name",
              "id": "2",
              "settings": {
                "min_doc_count": 1,
                "order": "desc",
                "orderBy": "1",
                "size": "10"
              },
              "type": "terms"
            }
          ],
          "datasource": {
            "type": "elasticsearch",
            "uid": "000000006"
          },
          "metrics": [
            {
              "field": "select field",
              "id": "1",
              "type": "count"
            }
          ],
          "query": "host.name:$apihost AND  source.address:$clientip",
          "refId": "A",
          "timeField": "@timestamp"
        }
      ],
      "title": "Hits by API host",
      "transformations": [
        {
          "id": "merge",
          "options": {
            "reducers": []
          }
        }
      ],
      "type": "table"
    },
    {
      "datasource": {
        "type": "elasticsearch",
        "uid": "000000006"
      },
      "fieldConfig": {
        "defaults": {
          "color": {
            "mode": "thresholds"
          },
          "custom": {
            "cellOptions": {
              "type": "auto"
            },
            "inspect": false
          },
          "decimals": 2,
          "displayName": "",
          "mappings": [],
          "thresholds": {
            "mode": "absolute",
            "steps": [
              {
                "color": "green",
                "value": null
              },
              {
                "color": "red",
                "value": 80
              }
            ]
          },
          "unit": "short"
        },
        "overrides": [
          {
            "matcher": {
              "id": "byName",
              "options": "source.address"
            },
            "properties": [
              {
                "id": "displayName",
                "value": "Client IP"
              },
              {
                "id": "unit",
                "value": "short"
              },
              {
                "id": "decimals",
                "value": 2
              },
              {
                "id": "custom.align"
              }
            ]
          },
          {
            "matcher": {
              "id": "byName",
              "options": "Count"
            },
            "properties": [
              {
                "id": "unit",
                "value": "locale"
              },
              {
                "id": "decimals",
                "value": 2
              },
              {
                "id": "custom.align"
              }
            ]
          }
        ]
      },
      "gridPos": {
        "h": 9,
        "w": 12,
        "x": 0,
        "y": 15
      },
      "id": 4,
      "links": [],
      "options": {
        "cellHeight": "sm",
        "footer": {
          "countRows": false,
          "fields": "",
          "reducer": [
            "sum"
          ],
          "show": false
        },
        "showHeader": true
      },
      "pluginVersion": "9.5.7",
      "targets": [
        {
          "bucketAggs": [
            {
              "field": "source.address",
              "id": "2",
              "settings": {
                "min_doc_count": 1,
                "order": "desc",
                "orderBy": "1",
                "size": "10"
              },
              "type": "terms"
            }
          ],
          "datasource": {
            "type": "elasticsearch",
            "uid": "000000006"
          },
          "metrics": [
            {
              "field": "select field",
              "id": "1",
              "type": "count"
            }
          ],
          "query": "host.name:$apihost AND source.address:$clientip",
          "refId": "A",
          "timeField": "@timestamp"
        }
      ],
      "title": "Hits by ClientIP",
      "transformations": [
        {
          "id": "merge",
          "options": {
            "reducers": []
          }
        }
      ],
      "type": "table"
    },
    {
      "datasource": {
        "type": "elasticsearch",
        "uid": "000000006"
      },
      "fieldConfig": {
        "defaults": {
          "color": {
            "mode": "thresholds"
          },
          "custom": {
            "cellOptions": {
              "type": "auto"
            },
            "inspect": false
          },
          "decimals": 2,
          "displayName": "",
          "mappings": [],
          "thresholds": {
            "mode": "absolute",
            "steps": [
              {
                "color": "green",
                "value": null
              },
              {
                "color": "red",
                "value": 80
              }
            ]
          },
          "unit": "short"
        },
        "overrides": [
          {
            "matcher": {
              "id": "byName",
              "options": "Count"
            },
            "properties": [
              {
                "id": "unit",
                "value": "locale"
              },
              {
                "id": "decimals",
                "value": 2
              },
              {
                "id": "custom.align"
              }
            ]
          },
          {
            "matcher": {
              "id": "byName",
              "options": "parameters.apikey"
            },
            "properties": [
              {
                "id": "displayName",
                "value": "API Key"
              }
            ]
          }
        ]
      },
      "gridPos": {
        "h": 9,
        "w": 12,
        "x": 12,
        "y": 15
      },
      "id": 9,
      "links": [],
      "options": {
        "cellHeight": "sm",
        "footer": {
          "countRows": false,
          "fields": "",
          "reducer": [
            "sum"
          ],
          "show": false
        },
        "showHeader": true
      },
      "pluginVersion": "9.5.7",
      "targets": [
        {
          "bucketAggs": [
            {
              "field": "parameters.apikey",
              "id": "2",
              "settings": {
                "min_doc_count": 1,
                "order": "desc",
                "orderBy": "1",
                "size": "10"
              },
              "type": "terms"
            }
          ],
          "datasource": {
            "type": "elasticsearch",
            "uid": "000000006"
          },
          "metrics": [
            {
              "field": "select field",
              "id": "1",
              "type": "count"
            }
          ],
          "query": "host.name:$apihost AND source.address:$clientip",
          "refId": "A",
          "timeField": "@timestamp"
        }
      ],
      "title": "Hits by API Key",
      "transformations": [
        {
          "id": "merge",
          "options": {
            "reducers": []
          }
        }
      ],
      "type": "table"
    },
    {
      "datasource": {
        "type": "elasticsearch",
        "uid": "000000006"
      },
      "fieldConfig": {
        "defaults": {
          "color": {
            "mode": "thresholds"
          },
          "custom": {
            "cellOptions": {
              "type": "auto"
            },
            "inspect": false
          },
          "decimals": 2,
          "displayName": "",
          "mappings": [],
          "thresholds": {
            "mode": "absolute",
            "steps": [
              {
                "color": "green",
                "value": null
              },
              {
                "color": "red",
                "value": 80
              }
            ]
          },
          "unit": "short"
        },
        "overrides": [
          {
            "matcher": {
              "id": "byName",
              "options": "Time"
            },
            "properties": [
              {
                "id": "displayName",
                "value": "Time"
              },
              {
                "id": "unit",
                "value": "time: YYYY-MM-DD HH:mm:ss"
              },
              {
                "id": "custom.align"
              }
            ]
          },
          {
            "matcher": {
              "id": "byName",
              "options": "Count"
            },
            "properties": [
              {
                "id": "unit",
                "value": "locale"
              },
              {
                "id": "decimals",
                "value": 2
              },
              {
                "id": "custom.align"
              }
            ]
          },
          {
            "matcher": {
              "id": "byName",
              "options": "endpoint"
            },
            "properties": [
              {
                "id": "displayName",
                "value": "Endpoint"
              },
              {
                "id": "unit",
                "value": "short"
              },
              {
                "id": "decimals",
                "value": 2
              },
              {
                "id": "custom.align"
              }
            ]
          }
        ]
      },
      "gridPos": {
        "h": 9,
        "w": 12,
        "x": 0,
        "y": 24
      },
      "id": 6,
      "links": [],
      "options": {
        "cellHeight": "sm",
        "footer": {
          "countRows": false,
          "fields": "",
          "reducer": [
            "sum"
          ],
          "show": false
        },
        "showHeader": true
      },
      "pluginVersion": "9.5.7",
      "targets": [
        {
          "bucketAggs": [
            {
              "field": "endpoint",
              "id": "2",
              "settings": {
                "min_doc_count": 1,
                "order": "desc",
                "orderBy": "1",
                "size": "10"
              },
              "type": "terms"
            }
          ],
          "datasource": {
            "type": "elasticsearch",
            "uid": "000000006"
          },
          "metrics": [
            {
              "field": "select field",
              "id": "1",
              "type": "count"
            }
          ],
          "query": "host.name:$apihost AND source.address:$clientip",
          "refId": "A",
          "timeField": "@timestamp"
        }
      ],
      "title": "Hits by Endpoint",
      "transformations": [
        {
          "id": "merge",
          "options": {
            "reducers": []
          }
        }
      ],
      "type": "table"
    },
    {
      "datasource": {
        "type": "elasticsearch",
        "uid": "000000006"
      },
      "fieldConfig": {
        "defaults": {
          "color": {
            "mode": "thresholds"
          },
          "custom": {
            "cellOptions": {
              "type": "auto"
            },
            "inspect": false
          },
          "decimals": 2,
          "displayName": "",
          "mappings": [],
          "thresholds": {
            "mode": "absolute",
            "steps": [
              {
                "color": "green",
                "value": null
              },
              {
                "color": "red",
                "value": 80
              }
            ]
          },
          "unit": "short"
        },
        "overrides": [
          {
            "matcher": {
              "id": "byName",
              "options": "Time"
            },
            "properties": [
              {
                "id": "displayName",
                "value": "Time"
              },
              {
                "id": "unit",
                "value": "time: YYYY-MM-DD HH:mm:ss"
              },
              {
                "id": "custom.align"
              }
            ]
          },
          {
            "matcher": {
              "id": "byName",
              "options": "Count"
            },
            "properties": [
              {
                "id": "unit",
                "value": "locale"
              },
              {
                "id": "decimals",
                "value": 2
              },
              {
                "id": "custom.align"
              }
            ]
          },
          {
            "matcher": {
              "id": "byName",
              "options": "endpoint_extension"
            },
            "properties": [
              {
                "id": "displayName",
                "value": "Endpoint Extension"
              },
              {
                "id": "unit",
                "value": "short"
              },
              {
                "id": "decimals",
                "value": 2
              },
              {
                "id": "custom.align"
              }
            ]
          }
        ]
      },
      "gridPos": {
        "h": 9,
        "w": 12,
        "x": 12,
        "y": 24
      },
      "id": 7,
      "links": [],
      "options": {
        "cellHeight": "sm",
        "footer": {
          "countRows": false,
          "fields": "",
          "reducer": [
            "sum"
          ],
          "show": false
        },
        "showHeader": true
      },
      "pluginVersion": "9.5.7",
      "targets": [
        {
          "bucketAggs": [
            {
              "field": "endpoint_extension",
              "id": "2",
              "settings": {
                "min_doc_count": 1,
                "order": "desc",
                "orderBy": "1",
                "size": "10"
              },
              "type": "terms"
            }
          ],
          "datasource": {
            "type": "elasticsearch",
            "uid": "000000006"
          },
          "metrics": [
            {
              "field": "select field",
              "id": "1",
              "type": "count"
            }
          ],
          "query": "host.name:$apihost AND source.address:$clientip",
          "refId": "A",
          "timeField": "@timestamp"
        }
      ],
      "title": "Hits by Endpoint Extension",
      "transformations": [
        {
          "id": "merge",
          "options": {
            "reducers": []
          }
        }
      ],
      "type": "table"
    }
  ],
  "refresh": "",
  "schemaVersion": 38,
  "style": "dark",
  "tags": [],
  "templating": {
    "list": [
      {
        "current": {
          "tags": [],
          "text": "All",
          "value": [
            "$__all"
          ]
        },
        "datasource": {
          "type": "elasticsearch",
          "uid": "000000006"
        },
        "definition": "{\"find\": \"terms\", \"field\": \"host.name\"}",
        "hide": 0,
        "includeAll": true,
        "label": "API Hostname",
        "multi": true,
        "name": "apihost",
        "options": [],
        "query": "{\"find\": \"terms\", \"field\": \"host.name\"}",
        "refresh": 2,
        "regex": "",
        "skipUrlSync": false,
        "sort": 0,
        "tagValuesQuery": "",
        "tagsQuery": "",
        "type": "query",
        "useTags": false
      },
      {
        "current": {
          "text": "All",
          "value": [
            "$__all"
          ]
        },
        "datasource": {
          "type": "elasticsearch",
          "uid": "000000006"
        },
        "definition": "{\"find\": \"terms\", \"field\": \"source.address\"}",
        "hide": 0,
        "includeAll": true,
        "label": "Client IP",
        "multi": true,
        "name": "clientip",
        "options": [],
        "query": "{\"find\": \"terms\", \"field\": \"source.address\"}",
        "refresh": 2,
        "regex": "",
        "skipUrlSync": false,
        "sort": 3,
        "tagValuesQuery": "",
        "tagsQuery": "",
        "type": "query",
        "useTags": false
      }
    ]
  },
  "time": {
    "from": "now-24h",
    "to": "now"
  },
  "timepicker": {
    "refresh_intervals": [
      "5s",
      "10s",
      "30s",
      "1m",
      "5m",
      "15m",
      "30m",
      "1h",
      "2h",
      "1d"
    ],
    "time_options": [
      "5m",
      "15m",
      "1h",
      "6h",
      "12h",
      "24h",
      "2d",
      "7d",
      "30d"
    ]
  },
  "timezone": "utc",
  "title": "API Overview",
  "uid": "ZKv7gyQZz",
  "version": 1,
  "weekStart": ""
}